{
  "ranger": {"class":"recon","tier":1,"effects":{"woods_move_cost":1},"note":"Woods and Rainforest cost 1 Movement."},
  "alpine": {"class":"recon","tier":1,"effects":{"hills_move_cost":1},"note":"Hills cost 1 Movement."},
  "sentry": {"class":"recon","tier":2,"requires":["ranger","alpine"],"effects":{"see_through_woods":1}},
  "guerrilla": {"class":"recon","tier":2,"requires":["ranger","alpine"],"effects":{"move_after_attack":1}},
  "spyglass": {"class":"recon","tier":3,"requires":["sentry"],"effects":{"sight":1}},
  "ambush": {"class":"recon","tier":3,"requires":["guerrilla"],"effects":{"combat_all":20}},
  "camouflage": {"class":"recon","tier":4,"requires":["spyglass","ambush"],"effects":{"camouflage":1}},

  "battlecry": {"class":"melee","tier":1,"effects":{"attack_vs_melee_ranged":7}},
  "tortoise": {"class":"melee","tier":1,"effects":{"defend_ranged":10}},
  "commando": {"class":"melee","tier":2,"requires":["battlecry","amphibious"],"effects":{"movement":1,"scale_cliffs":1}},
  "amphibious": {"class":"melee","tier":2,"requires":["tortoise","commando"],"effects":{"amphibious":1}},
  "zweihander": {"class":"melee","tier":3,"requires":["commando","amphibious"],"effects":{"vs_anti_cavalry":7}},
  "urban_warfare": {"class":"melee","tier":3,"requires":["commando","amphibious"],"effects":{"district_melee":10}},
  "elite_guard": {"class":"melee","tier":4,"requires":["zweihander","urban_warfare"],"effects":{"extra_attacks":1,"move_after_attack":1}},

  "volley": {"class":"ranged","tier":1,"effects":{"ranged_vs_land":5}},
  "garrison": {"class":"ranged","tier":1,"effects":{"district_defense":10}},
  "arrow_storm": {"class":"ranged","tier":2,"requires":["volley"],"effects":{"ranged_vs_units":7}},
  "incendiaries": {"class":"ranged","tier":2,"requires":["garrison"],"effects":{"ranged_vs_district":7}},
  "suppression": {"class":"ranged","tier":3,"requires":["arrow_storm","incendiaries"],"effects":{"zone_of_control":1}},
  "emplacement": {"class":"ranged","tier":3,"requires":["arrow_storm","incendiaries"],"effects":{"defend_city_attack":10}},
  "expert_marksman": {"class":"ranged","tier":4,"requires":["suppression","emplacement"],"effects":{"extra_attacks":1}},

  "echelon": {"class":"anti_cavalry","tier":1,"effects":{"vs_cavalry":5}},
  "thrust": {"class":"anti_cavalry","tier":1,"effects":{"vs_melee":5}},
  "square": {"class":"anti_cavalry","tier":2,"requires":["echelon"],"effects":{"support_multiplier":2}},
  "schiltron": {"class":"anti_cavalry","tier":2,"requires":["thrust"],"effects":{"defend_melee":10}},
  "redeploy": {"class":"anti_cavalry","tier":3,"requires":["square","schiltron"],"effects":{"movement":1}},
  "choke_points": {"class":"anti_cavalry","tier":3,"requires":["square","schiltron"],"effects":{"rough_defense":7}},
  "hold_the_line": {"class":"anti_cavalry","tier":4,"requires":["redeploy","choke_points"],"effects":{"adjacent_vs_cavalry":10}},

  "caparison": {"class":"light_cavalry","tier":1,"effects":{"vs_anti_cavalry":5}},
  "coursers": {"class":"light_cavalry","tier":1,"effects":{"attack_vs_ranged_siege":5}},
  "depredation": {"class":"light_cavalry","tier":2,"requires":["caparison"],"effects":{"pillage_cost":1}},
  "double_envelopment": {"class":"light_cavalry","tier":2,"requires":["coursers"],"effects":{"flanking_multiplier":2}},
  "spiking_the_guns": {"class":"light_cavalry","tier":3,"requires":["depredation","double_envelopment"],"effects":{"vs_siege":7}},
  "pursuit": {"class":"light_cavalry","tier":3,"requires":["depredation","double_envelopment"],"effects":{"movement":1}},
  "escort_mobility": {"class":"light_cavalry","tier":4,"requires":["spiking_the_guns","pursuit"],"effects":{"escort_mobility":1}},

  "charge": {"class":"heavy_cavalry","tier":1,"effects":{"vs_fortified":10}},
  "barding": {"class":"heavy_cavalry","tier":1,"effects":{"defend_ranged":7}},
  "marauding": {"class":"heavy_cavalry","tier":2,"requires":["charge","rout"],"effects":{"vs_unit_in_district":7}},
  "rout": {"class":"heavy_cavalry","tier":2,"requires":["barding","marauding"],"effects":{"vs_damaged":5}},
  "armor_piercing": {"class":"heavy_cavalry","tier":3,"requires":["marauding","rout"],"effects":{"vs_heavy_cavalry":7}},
  "reactive_armor": {"class":"heavy_cavalry","tier":3,"requires":["rout"],"effects":{"defend_heavy_anti":7}},
  "breakthrough": {"class":"heavy_cavalry","tier":4,"requires":["armor_piercing","reactive_armor"],"effects":{"extra_attacks":1}},

  "grape_shot": {"class":"siege","tier":1,"effects":{"siege_vs_land":7}},
  "crew_weapons": {"class":"siege","tier":1,"effects":{"defend_all":7}},
  "shrapnel": {"class":"siege","tier":2,"requires":["grape_shot"],"effects":{"siege_vs_land":10}},
  "shells": {"class":"siege","tier":2,"requires":["crew_weapons"],"effects":{"ranged_vs_district":10}},
  "advanced_rangefinding": {"class":"siege","tier":3,"requires":["shrapnel","shells"],"effects":{"siege_vs_naval":10}},
  "expert_crew": {"class":"siege","tier":3,"requires":["shrapnel","shells"],"effects":{"attack_after_move":1}},
  "forward_observers": {"class":"siege","tier":4,"requires":["advanced_rangefinding","expert_crew"],"effects":{"range":1}},

  "helmsman": {"class":"naval_melee","tier":1,"effects":{"movement":1}},
  "embolon": {"class":"naval_melee","tier":1,"effects":{"vs_naval":7}},
  "rutter": {"class":"naval_melee","tier":2,"requires":["helmsman"],"effects":{"sight":1}},
  "reinforced_hull": {"class":"naval_melee","tier":2,"requires":["embolon"],"effects":{"defend_ranged":10}},
  "convoy": {"class":"naval_melee","tier":3,"requires":["rutter","reinforced_hull"],"effects":{"formation_combat":10}},
  "auxiliary_ships": {"class":"naval_melee","tier":3,"requires":["rutter","reinforced_hull"],"effects":{"heal_anywhere":1}},
  "creeping_attack": {"class":"naval_melee","tier":4,"requires":["convoy","auxiliary_ships"],"effects":{"vs_naval_raider":14}},

  "line_of_battle": {"class":"naval_ranged","tier":1,"effects":{"ranged_vs_naval":7},"note":"+7 Ranged Strength against naval units."},
  "bombardment": {"class":"naval_ranged","tier":1,"effects":{"ranged_vs_district":7},"note":"+7 Ranged Strength against district defenses."},
  "preparatory_fire": {"class":"naval_ranged","tier":2,"requires":["line_of_battle"],"effects":{"ranged_vs_land":7},"note":"+7 Ranged Strength against land units."},
  "rolling_barrage": {"class":"naval_ranged","tier":2,"requires":["bombardment"],"effects":{"ranged_vs_district":10},"note":"+10 Ranged Strength against district defenses."},
  "supply_fleet": {"class":"naval_ranged","tier":3,"requires":["preparatory_fire","rolling_barrage"],"effects":{"heal_anywhere":1},"note":"May heal outside friendly territory."},
  "proximity_fuses": {"class":"naval_ranged","tier":3,"requires":["preparatory_fire","rolling_barrage"],"effects":{"defend_air":7},"note":"+7 Combat Strength when defending against air attacks."},
  "coincidence_rangefinding": {"class":"naval_ranged","tier":4,"requires":["supply_fleet","proximity_fuses"],"effects":{"range":1},"note":"+1 attack range."},

  "boarding": {"class":"naval_raider","tier":1,"effects":{"gold_from_naval_kill_pct":50},"note":"Gain Gold after defeating a naval unit."},
  "homing_torpedoes": {"class":"naval_raider","tier":1,"effects":{"ranged_vs_naval":10},"note":"+10 Ranged Strength against naval units."},
  "loot": {"class":"naval_raider","tier":2,"requires":["boarding"],"effects":{"coastal_raid_gold_pct":50},"note":"Gain additional Gold from coastal raids."},
  "silent_running": {"class":"naval_raider","tier":2,"requires":["homing_torpedoes"],"effects":{"move_after_attack":1},"note":"May move after attacking."},
  "observation": {"class":"naval_raider","tier":3,"requires":["loot","silent_running"],"effects":{"sight":1},"note":"+1 sight range."},
  "wolfpack": {"class":"naval_raider","tier":3,"requires":["loot","silent_running"],"effects":{"extra_attacks":1},"note":"+1 attack per turn."},
  "swift_keel": {"class":"naval_raider","tier":4,"requires":["observation","wolfpack"],"effects":{"movement":1},"note":"+1 Movement."},

  "flight_deck": {"class":"naval_carrier","tier":1,"effects":{"aircraft_slots":1},"note":"+1 aircraft slot."},
  "scout_planes": {"class":"naval_carrier","tier":1,"effects":{"sight":1},"note":"+1 sight range."},
  "hangar_deck": {"class":"naval_carrier","tier":2,"requires":["flight_deck","advanced_engines"],"effects":{"aircraft_slots":1},"note":"+1 aircraft slot."},
  "advanced_engines": {"class":"naval_carrier","tier":2,"requires":["scout_planes","hangar_deck"],"effects":{"movement":1},"note":"+1 Movement."},
  "folding_wings": {"class":"naval_carrier","tier":3,"requires":["hangar_deck","deck_crews"],"effects":{"aircraft_slots":1},"note":"+1 aircraft slot."},
  "deck_crews": {"class":"naval_carrier","tier":3,"requires":["advanced_engines","folding_wings"],"effects":{"heal_after_attack":1},"note":"May heal after attacking."},
  "supercarrier": {"class":"naval_carrier","tier":4,"requires":["folding_wings","deck_crews"],"effects":{"heal_anywhere":1},"note":"May heal outside friendly territory."}
}
